beadclust/__init__.py
beadclust/cli.py
beadclust/cluster.py
beadclust/data/config-template.yml
beadclust/data/seaflow_filter_slopes.csv
beadclust/db.py
beadclust/errors.py
beadclust/filter.py
beadclust/filter_params.py
beadclust/io.py
beadclust/particleops.py
beadclust/plot.py
beadclust-0.13.1.dist-info/WHEEL
beadclust-0.13.1.dist-info/entry_points.txt
beadclust-0.13.1.dist-info/METADATA
beadclust-0.13.1.dist-info/RECORD
