Metadata-Version: 2.3
Name: beadclust
Version: 0.13.1
Summary: Automated clustering of beads for the SeaFlow flow cytometer
Author: Chris T. Berthiaume
Author-email: Chris T. Berthiaume <chrisbee@uw.edu>
Requires-Dist: hdbscan>=0.8.40
Requires-Dist: jinja2>=3.1.6
Requires-Dist: jupyterlab>=4.4.5
Requires-Dist: matplotlib>=3.10.5
Requires-Dist: pandas>=2.3.1
Requires-Dist: papermill>=2.6.0
Requires-Dist: pyyaml>=6.0.2
Requires-Dist: seaflowpy>=14.5.2
Requires-Python: >=3.12, <3.14
